syntrac_opentelemetry/instrumentation/replicate/__init__.py
syntrac_opentelemetry/instrumentation/replicate/version.py
syntrac_opentelemetry_instrumentation_replicate-0.0.2.dist-info/METADATA
syntrac_opentelemetry_instrumentation_replicate-0.0.2.dist-info/WHEEL
syntrac_opentelemetry_instrumentation_replicate-0.0.2.dist-info/entry_points.txt
syntrac_opentelemetry_instrumentation_replicate-0.0.2.dist-info/RECORD
