Metadata-Version: 2.1
Name: syntrac-opentelemetry-instrumentation-replicate
Version: 0.0.2
Summary: OpenTelemetry Replicate instrumentation
Home-page: https://github.com/syntracAI/syntrac/tree/main/packages/python/opentelemetry-instrumentation-replicate
License: Apache-2.0
Author: Kartik Prajapati
Author-email: kartik@ktklab.org
Requires-Python: >=3.9,<4
Classifier: License :: OSI Approved :: Apache Software License
Classifier: Programming Language :: Python :: 3
Classifier: Programming Language :: Python :: 3.9
Classifier: Programming Language :: Python :: 3.10
Classifier: Programming Language :: Python :: 3.11
Classifier: Programming Language :: Python :: 3.12
Provides-Extra: instruments
Requires-Dist: opentelemetry-api (>=1.23.0,<2.0.0)
Requires-Dist: opentelemetry-instrumentation (==0.44b0)
Requires-Dist: opentelemetry-semantic-conventions (==0.44b0)
Requires-Dist: syntrac-opentelemetry-semantic-conventions-ai (==0.0.1)
Project-URL: Repository, https://github.com/syntracAI/syntrac/tree/main/packages/python/opentelemetry-instrumentation-replicate
